NumpyEssentialsDaiZhushiYuanma/README.md
NumpyEssentialsDaiZhushiYuanma/__init__.py
NumpyEssentialsDaiZhushiYuanma/__main__.py
NumpyEssentialsDaiZhushiYuanma/file.epub
NumpyEssentialsDaiZhushiYuanma/index.html
NumpyEssentialsDaiZhushiYuanma/css/__init__.py
NumpyEssentialsDaiZhushiYuanma/css/annotations.css
NumpyEssentialsDaiZhushiYuanma/css/main.css
NumpyEssentialsDaiZhushiYuanma/css/normalize.css
NumpyEssentialsDaiZhushiYuanma/css/popup.css
NumpyEssentialsDaiZhushiYuanma/font/__init__.py
NumpyEssentialsDaiZhushiYuanma/font/fontello.eot
NumpyEssentialsDaiZhushiYuanma/font/fontello.svg
NumpyEssentialsDaiZhushiYuanma/font/fontello.ttf
NumpyEssentialsDaiZhushiYuanma/font/fontello.woff
NumpyEssentialsDaiZhushiYuanma/img/__init__.py
NumpyEssentialsDaiZhushiYuanma/img/annotator-glyph-sprite.png
NumpyEssentialsDaiZhushiYuanma/img/annotator-icon-sprite.png
NumpyEssentialsDaiZhushiYuanma/img/apple-touch-icon.png
NumpyEssentialsDaiZhushiYuanma/img/cancelfullscreen.png
NumpyEssentialsDaiZhushiYuanma/img/close.png
NumpyEssentialsDaiZhushiYuanma/img/fullscreen.png
NumpyEssentialsDaiZhushiYuanma/img/loader.gif
NumpyEssentialsDaiZhushiYuanma/img/menu-icon.png
NumpyEssentialsDaiZhushiYuanma/img/save.png
NumpyEssentialsDaiZhushiYuanma/img/saved.png
NumpyEssentialsDaiZhushiYuanma/img/settings-s.png
NumpyEssentialsDaiZhushiYuanma/img/settings.png
NumpyEssentialsDaiZhushiYuanma/img/star.png
NumpyEssentialsDaiZhushiYuanma/js/__init__.py
NumpyEssentialsDaiZhushiYuanma/js/epub.js
NumpyEssentialsDaiZhushiYuanma/js/epub.min.js
NumpyEssentialsDaiZhushiYuanma/js/epub.min.map
NumpyEssentialsDaiZhushiYuanma/js/hooks.min.js
NumpyEssentialsDaiZhushiYuanma/js/hooks.min.map
NumpyEssentialsDaiZhushiYuanma/js/reader.js
NumpyEssentialsDaiZhushiYuanma/js/reader.js.map
NumpyEssentialsDaiZhushiYuanma/js/reader.min.js
NumpyEssentialsDaiZhushiYuanma/js/reader.min.map
NumpyEssentialsDaiZhushiYuanma/js/hooks/__init__.py
NumpyEssentialsDaiZhushiYuanma/js/hooks/extensions/__init__.py
numpy_essentials_dai_zhushi_yuanma-2024.3.3.0.dist-info/METADATA
numpy_essentials_dai_zhushi_yuanma-2024.3.3.0.dist-info/WHEEL
numpy_essentials_dai_zhushi_yuanma-2024.3.3.0.dist-info/entry_points.txt
numpy_essentials_dai_zhushi_yuanma-2024.3.3.0.dist-info/top_level.txt
numpy_essentials_dai_zhushi_yuanma-2024.3.3.0.dist-info/RECORD
